ontol/__init__.py
ontol/ai.py
ontol/cli.py
ontol/constants.py
ontol/oast.py
ontol/parser.py
ontol/plantuml.py
ontol/retranslator.py
ontol/serializer.py
ontol-2.14.1.dist-info/licenses/LICENSE
ontol-2.14.1.dist-info/METADATA
ontol-2.14.1.dist-info/WHEEL
ontol-2.14.1.dist-info/entry_points.txt
ontol-2.14.1.dist-info/top_level.txt
ontol-2.14.1.dist-info/RECORD
