Metadata-Version: 2.4
Name: ontol
Version: 2.14.1
Summary: A tool for parsing and visualizing ontology files written in the Ontol DSL
Author: Skvortsov Vladimir, Aptukov Mikhail, Markov Mikhail, Khamidullin Ilsaf, Afanasyev Andrew
License:                                  Apache License
Project-URL: Repository, https://github.com/vladimir-skvortsov/ontol
Requires-Python: >=3.9
License-File: LICENSE
Requires-Dist: requests==2.32.3
Requires-Dist: watchdog==3.0.0
Requires-Dist: plantuml==0.3.0
Requires-Dist: pytest==8.3.4
Requires-Dist: six==1.17.0
Requires-Dist: pytest-cov==6.0.0
Requires-Dist: sly==0.5
Requires-Dist: langchain==0.3.9
Requires-Dist: langchain-core==0.3.21
Requires-Dist: langchain-community==0.3.9
Requires-Dist: unidecode==1.3.8
Dynamic: license-file
